windeurope72hours/__init__.py
windeurope72hours/client.py
windeurope72hours-0.1.3.dist-info/LICENSE
windeurope72hours-0.1.3.dist-info/METADATA
windeurope72hours-0.1.3.dist-info/WHEEL
windeurope72hours-0.1.3.dist-info/RECORD
