Metadata-Version: 2.1
Name: windeurope72hours
Version: 0.1.3
Summary: 
License: MIT
Author: Marcus Lugg
Author-email: marcus@octue.com
Requires-Python: >=3.9,<4.0
Classifier: License :: OSI Approved :: MIT License
Classifier: Programming Language :: Python :: 3
Classifier: Programming Language :: Python :: 3.9
Classifier: Programming Language :: Python :: 3.10
Classifier: Programming Language :: Python :: 3.11
Requires-Dist: h3 (>=3.7.6,<4.0.0)
Requires-Dist: requests (>=2.28.2,<3.0.0)
